Metadata-Version: 2.1
Name: um7py
Version: 0.5.18
Summary: Redshift Labs Pty Ltd UM7 Python Driver
Home-page: https://github.com/RedshiftLabsPtyLtd/um7py
Author: Redshift Labs Pty Ltd, Dr. Konstantin Selyunin
Author-email: selyunin.k.v@gmail.com
License: MIT
Platform: UNKNOWN
Classifier: Programming Language :: Python :: 3.7
Classifier: License :: OSI Approved :: MIT License
Classifier: Operating System :: POSIX
Requires: pyserial
Requires-Dist: pyserial
